pylisencesign/__init__.py
pylisencesign/pylisencesign.py
pylisencesign-1.0.0.dist-info/METADATA
pylisencesign-1.0.0.dist-info/WHEEL
pylisencesign-1.0.0.dist-info/top_level.txt
pylisencesign-1.0.0.dist-info/RECORD
