Metadata-Version: 2.1
Name: pylisencesign
Version: 1.0.0
Summary: A Certificate Signing Algorithm Suitable for Small Devices
Home-page: UNKNOWN
Author: Arikido
Author-email: arikido.brown@proton.me
License: MIT
Platform: UNKNOWN
Classifier: Programming Language :: Python :: 3
Classifier: License :: OSI Approved :: MIT License
Classifier: Operating System :: OS Independent
Requires-Dist: datetime
Requires-Dist: pycryptodome
